LICENSE
README.md
pyproject.toml
setup.py
src/wavpack_numcodecs/__init__.py
src/wavpack_numcodecs/compat_ext.c
src/wavpack_numcodecs/compat_ext.pxd
src/wavpack_numcodecs/compat_ext.pyx
src/wavpack_numcodecs/globals.py
src/wavpack_numcodecs/libwavpack.so.1
src/wavpack_numcodecs/wavpack.c
src/wavpack_numcodecs/wavpack.pyx
src/wavpack_numcodecs.egg-info/PKG-INFO
src/wavpack_numcodecs.egg-info/SOURCES.txt
src/wavpack_numcodecs.egg-info/dependency_links.txt
src/wavpack_numcodecs.egg-info/entry_points.txt
src/wavpack_numcodecs.egg-info/requires.txt
src/wavpack_numcodecs.egg-info/top_level.txt
src/wavpack_numcodecs/include/wavpack/wavpack.h
src/wavpack_numcodecs/libraries/5.6.0/linux-x86_64-glibc2.35/libwavpack.so
src/wavpack_numcodecs/libraries/5.6.0/windows-x86_32/wavpackdll.dll
src/wavpack_numcodecs/libraries/5.6.0/windows-x86_32/wavpackdll.lib
src/wavpack_numcodecs/libraries/5.6.0/windows-x86_64/wavpackdll.dll
src/wavpack_numcodecs/libraries/5.6.0/windows-x86_64/wavpackdll.lib
src/wavpack_numcodecs/libraries/5.7.0/linux-x86_64-glibc2.31/libwavpack.so
src/wavpack_numcodecs/libraries/5.7.0/linux-x86_64-glibc2.35/libwavpack.so
src/wavpack_numcodecs/libraries/5.7.0/linux-x86_64-glibc2.39/libwavpack.so
src/wavpack_numcodecs/libraries/5.7.0/windows-x86_32/wavpackdll.dll
src/wavpack_numcodecs/libraries/5.7.0/windows-x86_32/wavpackdll.lib
src/wavpack_numcodecs/libraries/5.7.0/windows-x86_64/wavpackdll.dll
src/wavpack_numcodecs/libraries/5.7.0/windows-x86_64/wavpackdll.lib
src/wavpack_numcodecs/libraries/5.8.0/linux-x86_64-glibc2.35/libwavpack.so
src/wavpack_numcodecs/libraries/5.8.0/linux-x86_64-glibc2.39/libwavpack.so
src/wavpack_numcodecs/libraries/5.8.0/linux-x86_64-glibc2.39/libwavpack.so.1
src/wavpack_numcodecs/libraries/5.8.0/windows-x86_32/wavpackdll.dll
src/wavpack_numcodecs/libraries/5.8.0/windows-x86_32/wavpackdll.lib
src/wavpack_numcodecs/libraries/5.8.0/windows-x86_64/wavpackdll.dll
src/wavpack_numcodecs/libraries/5.8.0/windows-x86_64/wavpackdll.lib
src/wavpack_numcodecs/src/decoder.c
src/wavpack_numcodecs/src/encoder.c
tests/test_imports.py
tests/test_wavpack_codec.py