Metadata-Version: 2.1
Name: wavpack-numcodecs
Version: 0.2.3
Summary: Numcodecs implementation of WavPack audio codec.
Author-email: Alessio Buccino <alessiop.buccino@gmail.com>, David Bryant <david@wavpack.com>
License: MIT
Project-URL: Homepage, https://github.com/AllenNeuralDynamics/wavpack-numcodecs
Keywords: example,project
Classifier: Programming Language :: Python :: 3
Classifier: License :: OSI Approved :: MIT License
Classifier: Operating System :: OS Independent
Provides-Extra: test
Provides-Extra: test_no_cython
License-File: LICENSE
